storages/__init__.py
storages/bases.py
storages/exceptions.py
storages/fields.py
storages/storages.py
storages/backends/__init__.py
peewee_storages-0.0.2.dist-info/LICENSE
peewee_storages-0.0.2.dist-info/METADATA
peewee_storages-0.0.2.dist-info/WHEEL
peewee_storages-0.0.2.dist-info/top_level.txt
peewee_storages-0.0.2.dist-info/RECORD
